mkdocs_graph_view/__init__.py
mkdocs_graph_view/config.py
mkdocs_graph_view/plugin.py
mkdocs_graph_view/assets/javascripts/graph.js
mkdocs_graph_view/assets/stylesheets/graph.css
mkdocs_graph_view-0.2.0.dist-info/licenses/LICENSE
mkdocs_graph_view-0.2.0.dist-info/METADATA
mkdocs_graph_view-0.2.0.dist-info/WHEEL
mkdocs_graph_view-0.2.0.dist-info/entry_points.txt
mkdocs_graph_view-0.2.0.dist-info/top_level.txt
mkdocs_graph_view-0.2.0.dist-info/RECORD
