Metadata-Version: 2.4
Name: mkdocs-graph-view
Version: 0.2.0
Summary: A MkDocs plugin for creating interactive graph visualizations of page connections
Author: Sawyer Rensel
License: GPL-3.0-or-later
Project-URL: Homepage, https://github.com/sawyerrensel/mkdocs-graph-view
Project-URL: Documentation, https://sawyerrensel.github.io/mkdocs-graph-view/
Project-URL: Repository, https://github.com/sawyerrensel/mkdocs-graph-view
Project-URL: Issues, https://github.com/sawyerrensel/mkdocs-graph-view/issues
Keywords: mkdocs,plugin,graph,visualization,d3js,network
Classifier: Development Status :: 4 - Beta
Classifier: Intended Audience :: Developers
Classifier: License :: OSI Approved :: GNU General Public License v3 or later (GPLv3+)
Classifier: Programming Language :: Python :: 3
Classifier: Programming Language :: Python :: 3.8
Classifier: Programming Language :: Python :: 3.9
Classifier: Programming Language :: Python :: 3.10
Classifier: Programming Language :: Python :: 3.11
Classifier: Programming Language :: Python :: 3.12
Classifier: Topic :: Documentation
Classifier: Topic :: Software Development :: Documentation
Requires-Python: >=3.8
License-File: LICENSE
Requires-Dist: mkdocs>=1.4.0
Dynamic: license-file
